taxbill/__init__.py
taxbill/__main__.py
taxbill/analyser.py
taxbill/calculator.py
taxbill/cli.py
taxbill/optimiser.py
taxbill/rates.yml
taxbill-0.1.5.dist-info/entry_points.txt
taxbill-0.1.5.dist-info/LICENSE.txt
taxbill-0.1.5.dist-info/WHEEL
taxbill-0.1.5.dist-info/METADATA
taxbill-0.1.5.dist-info/RECORD
